metathing/__init__.py
metathing/alarmer.py
metathing/application.py
metathing/config.py
metathing/device.py
metathing/http.py
metathing/logger.py
metathing/metathing.py
metathing/mqtt.py
metathing/service.py
metathing-0.3.6.dist-info/METADATA
metathing-0.3.6.dist-info/WHEEL
metathing-0.3.6.dist-info/top_level.txt
metathing-0.3.6.dist-info/RECORD
