Metadata-Version: 2.1
Name: metathing
Version: 0.3.6
Summary: MT-Service Python SDK
Author: Mang Shao
License: N/A
Requires-Dist: pyyaml
Requires-Dist: paho-mqtt
